getwebfolder/__init__.py
getwebfolder/__main__.py
getwebfolder-0.1.0.dist-info/WHEEL
getwebfolder-0.1.0.dist-info/METADATA
getwebfolder-0.1.0.dist-info/RECORD
